{
  "pageTitle": "Main Menu",
  "children": [
    {
      "type": "nested",
      "name": "Menu Item A",
      "children": [
        {
          "type": "placeholder",
          "name": "Menu Item A1"
        },
        {
          "type": "nested",
          "name": "Menu Item A2",
          "children": [
            {
              "type": "placeholder",
              "name": "Menu Item A21"
            },
            {
              "type": "nested",
              "name": "Menu Item A22",
              "children": [
                {
                  "type": "form",
                  "name": "Menu Item A221 (with Form)",
                  "formFields": [
                    {
                      "type": "email",
                      "name": "email",
                      "label": "Email"
                    },
                    {
                      "type": "text",
                      "name": "username",
                      "label": "Username"
                    },
                    {
                      "type": "password",
                      "name": "password",
                      "label": "Password"
                    }
                  ]
                },
                {
                  "type": "placeholder",
                  "name": "Menu Item A222"
                }
              ]
            }
          ]
        },
        {
          "type": "placeholder",
          "name": "Menu Item A3"
        }
      ]
    },
    {
      "type": "form",
      "name": "Menu Item B (with Form)",
      "formFields": [
        {
          "type": "text",
          "name": "username",
          "label": "Username"
        },
        {
          "type": "password",
          "name": "password",
          "label": "Password"
        },
        {
          "type": "dropdown",
          "name": "state",
          "options":[
            "ACT","NSW","NT","QLD","SA","TAS","VIC","WA"
          ],
          "label": "State"
        }
      ]
    },
    {
      "type": "placeholder",
      "name": "Menu Item C"
    },
    {
      "type": "placeholder",
      "name": "Menu Item D"
    },
    {
      "type": "placeholder",
      "name": "Menu Item E"
    },
    {
      "type": "placeholder",
      "name": "Menu Item F"
    }
  ]
}